easycnn/__init__.py
easycnn/models.py
easycnn/predictor.py
easycnn/trainer.py
easycnn/visualizer.py
easycnn-0.1.0.dist-info/LICENSE
easycnn-0.1.0.dist-info/METADATA
easycnn-0.1.0.dist-info/WHEEL
easycnn-0.1.0.dist-info/top_level.txt
easycnn-0.1.0.dist-info/RECORD
