Metadata-Version: 2.1
Name: easycnn
Version: 0.1.0
Summary: EasyCNN: A library to create, train, and use custom CNN models with ease.
Home-page: https://github.com/yadavsidhant/easycnn
Author: Sidhant Yadav
Author-email: supersidhant10@gmail.com
License: UNKNOWN
Project-URL: Bug Tracker, https://github.com/yadavsidhant/easycnn/issues
Project-URL: Documentation, https://github.com/yadavsidhant/easycnn#readme
Project-URL: Youtube, https://www.youtube.com/@SidhantKYadav
Platform: UNKNOWN
Classifier: Programming Language :: Python :: 3
Classifier: License :: OSI Approved :: MIT License
Classifier: Operating System :: OS Independent
Classifier: Intended Audience :: Developers
Classifier: Topic :: Software Development :: Libraries :: Python Modules
Requires-Python: >=3.6
License-File: LICENSE
Requires-Dist: tensorflow >=2.0
Requires-Dist: pandas
Requires-Dist: matplotlib
Requires-Dist: scikit-learn
